{
  "id": "install/summary",
  "title": "Installing Colony",
  "description": "Follow the steps to install Colony in a virtual Vagrant environment",
  "source": "@site/docs/install/summary.md",
  "sourceDirName": "install",
  "slug": "/install/summary",
  "permalink": "/docs/next/install/summary",
  "draft": false,
  "unlisted": false,
  "tags": [],
  "version": "current",
  "frontMatter": {
    "title": "Installing Colony",
    "description": "Follow the steps to install Colony in a virtual Vagrant environment"
  },
  "sidebar": "myAutogeneratedSidebar",
  "previous": {
    "title": "Getting Started",
    "permalink": "/docs/next/install/"
  },
  "next": {
    "title": "Vagrant VM",
    "permalink": "/docs/next/install/vagrant"
  }
}